{
  "generator-jhipster": {
    "applicationType": "monolith",
    "gitCompany": "",
    "baseName": "jhipsterSampleApplication",
    "packageName": "com.mycompany.myapp",
    "packageFolder": "com/mycompany/myapp",
    "serverPort": 8080,
    "serviceDiscoveryType": false,
    "authenticationType": "jwt",
    "uaaBaseName": "../uaa",
    "cacheProvider": "ehcache",
    "enableHibernateCache": true,
    "websocket": false,
    "databaseType": "sql",
    "devDatabaseType": "h2Disk",
    "prodDatabaseType": "mysql",
    "searchEngine": false,
    "enableSwaggerCodegen": false,
    "messageBroker": false,
    "buildTool": "maven",
    "useSass": true,
    "clientPackageManager": "npm",
    "testFrameworks": ["gatling", "cucumber", "protractor"],
    "enableTranslation": true,
    "nativeLanguage": "fr",
    "languages": ["en", "fr"],
    "clientFramework": "angularX",
    "jhiPrefix": "jhi",
    "jhipsterVersion": "6.9.1",
    "jwtSecretKey": "MzA0ZjVhMTlkZjQ4MmU2MDZjYjVjN2E2ZDE5MDhkMzQyMjhhNmFiNmM0M2Q3ZDBlNTRmZjQxNjBlMWI4MzFlMzQ3MTJkMDE5YzNmYzU1NTc2ODY4NWEyYTJkMzU1ZjNlYmMzNzlmYzBkZWUxMGIyMjg4NDlkNTFlNWI3NzEyNDA=",
    "embeddableLaunchScript": false,
    "clientTheme": "none",
    "creationTimestamp": 1593201513041,
    "entitySuffix": "",
    "dtoSuffix": "DTO",
    "otherModules": [],
    "blueprints": [],
    "prettierJava": true
  },
  "git-provider": "GitHub",
  "git-company": "ahmedguidjali19",
  "repository-name": "jhipster-sample-application"
}
